{
  "anand_vihar": {
    "predicted_aqi_24h": 212.0,
    "history_points": 116
  },
  "rk_puram": {
    "predicted_aqi_24h": 246.9,
    "history_points": 116
  },
  "punjabi_bagh": {
    "predicted_aqi_24h": 153.7,
    "history_points": 111
  },
  "ito": {
    "predicted_aqi_24h": 127.7,
    "history_points": 116
  },
  "dwarka": {
    "predicted_aqi_24h": 281.2,
    "history_points": 110
  },
  "rohini": {
    "predicted_aqi_24h": 146.8,
    "history_points": 116
  },
  "okhla": {
    "predicted_aqi_24h": 224.5,
    "history_points": 115
  },
  "wazirpur": {
    "predicted_aqi_24h": 177.2,
    "history_points": 116
  },
  "vivek_vihar": {
    "predicted_aqi_24h": 145.6,
    "history_points": 113
  },
  "noida_sec62": {
    "predicted_aqi_24h": 150.2,
    "history_points": 116
  },
  "gurugram_sec51": {
    "predicted_aqi_24h": 69.3,
    "history_points": 102
  },
  "ghaziabad_sanjay_nagar": {
    "predicted_aqi_24h": 128.9,
    "history_points": 116
  }
}