{
  "anand_vihar": {
    "predicted_aqi_24h": 212.1,
    "history_points": 139
  },
  "rk_puram": {
    "predicted_aqi_24h": 198.6,
    "history_points": 139
  },
  "punjabi_bagh": {
    "predicted_aqi_24h": 135.7,
    "history_points": 134
  },
  "ito": {
    "predicted_aqi_24h": 109.4,
    "history_points": 139
  },
  "dwarka": {
    "predicted_aqi_24h": 189.2,
    "history_points": 133
  },
  "rohini": {
    "predicted_aqi_24h": 135.3,
    "history_points": 139
  },
  "okhla": {
    "predicted_aqi_24h": 150.5,
    "history_points": 138
  },
  "wazirpur": {
    "predicted_aqi_24h": 160.2,
    "history_points": 134
  },
  "vivek_vihar": {
    "predicted_aqi_24h": 128.3,
    "history_points": 136
  },
  "noida_sec62": {
    "predicted_aqi_24h": 136.7,
    "history_points": 139
  },
  "gurugram_sec51": {
    "predicted_aqi_24h": 247.9,
    "history_points": 120
  },
  "ghaziabad_sanjay_nagar": {
    "predicted_aqi_24h": 136.2,
    "history_points": 139
  }
}